standarted_logger/__init__.py
standarted_logger/logger.py
standarted_logger-0.0.6.dist-info/METADATA
standarted_logger-0.0.6.dist-info/WHEEL
standarted_logger-0.0.6.dist-info/RECORD
