Metadata-Version: 2.3
Name: standarted-logger
Version: 0.0.6
Summary: 
Author: Andrey Linyushin
Author-email: 89202979894@mail.ru
Requires-Python: >=3.10
Classifier: Programming Language :: Python :: 3
Classifier: Programming Language :: Python :: 3.10
Classifier: Programming Language :: Python :: 3.11
Classifier: Programming Language :: Python :: 3.12
Classifier: Programming Language :: Python :: 3.13
